visionz/__init__.py
visionz-0.0.3.dist-info/entry_points.txt
visionz-0.0.3.dist-info/LICENSE
visionz-0.0.3.dist-info/WHEEL
visionz-0.0.3.dist-info/METADATA
visionz-0.0.3.dist-info/RECORD
