Metadata-Version: 2.1
Name: visionz
Version: 0.0.3
Summary: vision
Author-email: xinetzone <735613050@qq.com>
Maintainer-email: xinetzone <735613050@qq.com>
Requires-Python: >=3.8
Classifier: Development Status :: 4 - Beta
Classifier: Programming Language :: Python :: 3
Classifier: Framework :: Sphinx
Classifier: Framework :: Sphinx :: Theme
Classifier: License :: OSI Approved :: Apache Software License
Classifier: Operating System :: OS Independent
Requires-Dist: d2py
Requires-Dist: streamlit
Requires-Dist: plotly
Requires-Dist: pytest-cov ; extra == "coverage"
Requires-Dist: pytest-regressions ; extra == "coverage"
Requires-Dist: codecov ; extra == "coverage"
Requires-Dist: vision[test] ; extra == "coverage"
Requires-Dist: pyyaml ; extra == "dev"
Requires-Dist: pre-commit ; extra == "dev"
Requires-Dist: vision[coverage] ; extra == "dev"
Requires-Dist: myst-nb ; extra == "doc"
Requires-Dist: xyzstyle ; extra == "doc"
Requires-Dist: ipywidgets>=8.0.2 ; extra == "doc"
Requires-Dist: sphinxext-rediraffe ; extra == "doc"
Requires-Dist: sphinx-copybutton ; extra == "doc"
Requires-Dist: plotly-geo ; extra == "doc"
Requires-Dist: sphinx-plotly-directive ; extra == "doc"
Requires-Dist: jupyter-dash ; extra == "doc"
Requires-Dist: sklearn-xarray ; extra == "doc"
Requires-Dist: pip-tools ; extra == "doc"
Requires-Dist: rtree ; extra == "doc"
Requires-Dist: ipykernel ; extra == "doc"
Requires-Dist: osmnx ; extra == "doc"
Requires-Dist: PyKrige ; extra == "doc"
Requires-Dist: census ; extra == "doc"
Requires-Dist: us ; extra == "doc"
Requires-Dist: rasterio ; extra == "doc"
Requires-Dist: kaleido ; extra == "doc"
Requires-Dist: pytest ; extra == "test"
Requires-Dist: vision[doc] ; extra == "test"
Project-URL: Home, https://github.com/xinetzone/vision
Provides-Extra: coverage
Provides-Extra: dev
Provides-Extra: doc
Provides-Extra: test
